iden/__init__.py
iden/constants.py
iden/py.typed
iden/data/__init__.py
iden/data/generator/__init__.py
iden/data/generator/base.py
iden/data/generator/vanilla.py
iden/dataset/__init__.py
iden/dataset/base.py
iden/dataset/exceptions.py
iden/dataset/loading.py
iden/dataset/vanilla.py
iden/dataset/generator/__init__.py
iden/dataset/generator/base.py
iden/dataset/generator/vanilla.py
iden/dataset/loader/__init__.py
iden/dataset/loader/base.py
iden/dataset/loader/vanilla.py
iden/io/__init__.py
iden/io/base.py
iden/io/cloudpickle.py
iden/io/joblib.py
iden/io/json.py
iden/io/loading.py
iden/io/pickle.py
iden/io/registry.py
iden/io/text.py
iden/io/torch.py
iden/io/utils.py
iden/io/yaml.py
iden/io/safetensors/__init__.py
iden/io/safetensors/loaders.py
iden/io/safetensors/savers.py
iden/shard/__init__.py
iden/shard/base.py
iden/shard/cloudpickle.py
iden/shard/dict.py
iden/shard/exceptions.py
iden/shard/file.py
iden/shard/in_memory.py
iden/shard/joblib.py
iden/shard/json.py
iden/shard/loading.py
iden/shard/pickle.py
iden/shard/safetensors.py
iden/shard/torch.py
iden/shard/tuple.py
iden/shard/utils.py
iden/shard/yaml.py
iden/shard/generator/__init__.py
iden/shard/generator/base.py
iden/shard/generator/cloudpickle.py
iden/shard/generator/dict.py
iden/shard/generator/file.py
iden/shard/generator/joblib.py
iden/shard/generator/json.py
iden/shard/generator/pickle.py
iden/shard/generator/safetensors.py
iden/shard/generator/torch.py
iden/shard/generator/tuple.py
iden/shard/generator/yaml.py
iden/shard/loader/__init__.py
iden/shard/loader/base.py
iden/shard/loader/cloudpickle.py
iden/shard/loader/dict.py
iden/shard/loader/file.py
iden/shard/loader/joblib.py
iden/shard/loader/json.py
iden/shard/loader/pickle.py
iden/shard/loader/safetensors.py
iden/shard/loader/torch.py
iden/shard/loader/tuple.py
iden/shard/loader/yaml.py
iden/testing/__init__.py
iden/testing/fixtures.py
iden/utils/__init__.py
iden/utils/format.py
iden/utils/imports.py
iden/utils/time.py
iden-0.4.0.dist-info/METADATA
iden-0.4.0.dist-info/WHEEL
iden-0.4.0.dist-info/licenses/LICENSE
iden-0.4.0.dist-info/RECORD
