Metadata-Version: 2.4
Name: iden
Version: 0.4.0
Dynamic: Maintainer
Dynamic: Maintainer-email
Summary: simple library to manage a dataset of shards to train machine learning models
Project-URL: homepage, https://github.com/durandtibo/iden
Project-URL: repository, https://github.com/durandtibo/iden
Project-URL: documentation, https://durandtibo.github.io/iden/
Author-email: Thibaut Durand <durand.tibo+gh@gmail.com>
License-Expression: BSD-3-Clause
License-File: LICENSE
Keywords: dataset,shard
Classifier: Development Status :: 4 - Beta
Classifier: Intended Audience :: Developers
Classifier: Intended Audience :: Information Technology
Classifier: Intended Audience :: Science/Research
Classifier: License :: OSI Approved :: BSD License
Classifier: Operating System :: POSIX :: Linux
Classifier: Programming Language :: Python :: 3.10
Classifier: Programming Language :: Python :: 3.11
Classifier: Programming Language :: Python :: 3.12
Classifier: Programming Language :: Python :: 3.13
Classifier: Programming Language :: Python :: 3.14
Classifier: Topic :: Scientific/Engineering
Classifier: Topic :: Scientific/Engineering :: Artificial Intelligence
Classifier: Topic :: Software Development :: Libraries
Requires-Python: >=3.10
Requires-Dist: coola<2.0,>=1.0
Requires-Dist: objectory<1.0,>=0.3.0
Provides-Extra: all
Requires-Dist: cloudpickle<4.0,>=3.0; extra == 'all'
Requires-Dist: joblib<2.0,>=1.3; extra == 'all'
Requires-Dist: numpy<3.0,>=1.24; extra == 'all'
Requires-Dist: pyyaml<7.0,>=6.0; extra == 'all'
Requires-Dist: safetensors<1.0,>=0.6; extra == 'all'
Requires-Dist: torch<2.3,>=2.0; (sys_platform == 'darwin' and platform_machine != 'arm64' and python_version < '3.13') and extra == 'all'
Requires-Dist: torch<3.0,>=2.0; (sys_platform == 'linux' or (sys_platform == 'darwin' and platform_machine == 'arm64')) and extra == 'all'
Provides-Extra: cloudpickle
Requires-Dist: cloudpickle<4.0,>=3.0; extra == 'cloudpickle'
Provides-Extra: joblib
Requires-Dist: joblib<2.0,>=1.3; extra == 'joblib'
Provides-Extra: numpy
Requires-Dist: numpy<3.0,>=1.24; extra == 'numpy'
Provides-Extra: pyyaml
Requires-Dist: pyyaml<7.0,>=6.0; extra == 'pyyaml'
Provides-Extra: safetensors
Requires-Dist: safetensors<1.0,>=0.6; extra == 'safetensors'
Provides-Extra: torch
Requires-Dist: torch<2.3,>=2.0; (sys_platform == 'darwin' and platform_machine != 'arm64' and python_version < '3.13') and extra == 'torch'
Requires-Dist: torch<3.0,>=2.0; (sys_platform == 'linux' or (sys_platform == 'darwin' and platform_machine == 'arm64')) and extra == 'torch'
